.gitignore
README
setup.py
jsonish/.gitignore
jsonish/__init__.py
jsonish/json.py
jsonish/pythonjson.py
jsonish.egg-info/PKG-INFO
jsonish.egg-info/SOURCES.txt
jsonish.egg-info/dependency_links.txt
jsonish.egg-info/requires.txt
jsonish.egg-info/top_level.txt
jsonish.egg-info/zip-safe