Metadata-Version: 1.0
Name: jsonish
Version: 0.1.1
Summary: extensible json extension lib. Includes module for python types (datetime, date, decimal, time)
Home-page: http://ish.io
Author: Tim Parkin & Matt Goodall
Author-email: info@timparkin.co.uk
License: UNKNOWN
Platform: UNKNOWN
